geoflow/__init__.py
geoflow/hooks/__init__.py
geoflow/hooks/ingest_postgis_hook.py
geoflow/operators/__init__.py
geoflow/operators/ingest_postgis_operator.py
geoflow/operators/ingest_wfs.py
geoflow-0.0.1.dist-info/METADATA
geoflow-0.0.1.dist-info/WHEEL
geoflow-0.0.1.dist-info/top_level.txt
geoflow-0.0.1.dist-info/RECORD
