Metadata-Version: 2.1
Name: geoflow
Version: 0.0.1
Summary: Airflow plugin to integrate geospatial data
Home-page: https://github.com/JulesHuisman/geoflow
Author: Jules Huisman
Author-email: jules.huisman@quantile.nl
License: MIT
Platform: UNKNOWN
Classifier: License :: OSI Approved :: MIT License
Classifier: Programming Language :: Python :: 3
Classifier: Programming Language :: Python :: 3.7
